duosubs/__init__.py
duosubs/py.typed
duosubs/cli/__init__.py
duosubs/cli/main.py
duosubs/common/__init__.py
duosubs/common/constants.py
duosubs/common/enums.py
duosubs/common/exceptions.py
duosubs/common/types.py
duosubs/core/__init__.py
duosubs/core/merge_pipeline.py
duosubs/core/merger.py
duosubs/io/__init__.py
duosubs/io/loader.py
duosubs/io/utils.py
duosubs/io/writer.py
duosubs/subtitle/__init__.py
duosubs/subtitle/data.py
duosubs/subtitle/field.py
duosubs/subtitle/tokenizer.py
duosubs/webui/__init__.py
duosubs/webui/assets/merging_mode_info.html
duosubs/webui/assets/title.html
duosubs/webui/manager/__init__.py
duosubs/webui/manager/model_manager.py
duosubs/webui/monitor/__init__.py
duosubs/webui/monitor/common.py
duosubs/webui/monitor/memory_monitor.py
duosubs/webui/ui/__init__.py
duosubs/webui/ui/common.py
duosubs/webui/ui/constants.py
duosubs/webui/ui/events.py
duosubs/webui/ui/layout.py
duosubs-1.1.0.dist-info/licenses/LICENSE
duosubs-1.1.0.dist-info/METADATA
duosubs-1.1.0.dist-info/WHEEL
duosubs-1.1.0.dist-info/entry_points.txt
duosubs-1.1.0.dist-info/top_level.txt
duosubs-1.1.0.dist-info/RECORD
