Metadata-Version: 2.4
Name: duosubs
Version: 1.1.0
Summary: Semantic subtitle aligner and merger for bilingual subtitle syncing.
Author: CK-Explorer 
License-Expression: Apache-2.0
Project-URL: Homepage, https://github.com/CK-Explorer/DuoSubs
Project-URL: Repository, https://github.com/CK-Explorer/DuoSubs
Project-URL: Documentation, https://duosubs.readthedocs.io/en/latest/
Keywords: subtitles,alignment,merging,sentence-transformers,sentence-similarity,bilingual,nlp
Classifier: Development Status :: 4 - Beta
Classifier: Intended Audience :: Developers
Classifier: Intended Audience :: End Users/Desktop
Classifier: Topic :: Text Processing :: Linguistic
Classifier: Topic :: Software Development :: Libraries :: Python Modules
Classifier: Topic :: Utilities
Classifier: Programming Language :: Python :: 3.10
Classifier: Programming Language :: Python :: 3.11
Classifier: Programming Language :: Python :: 3.12
Classifier: Programming Language :: Python :: 3.13
Classifier: Operating System :: OS Independent
Requires-Python: >=3.10
License-File: LICENSE
Requires-Dist: charset_normalizer<4.0,>=3.3.2
Requires-Dist: fastdtw<1.0,>=0.3.4
Requires-Dist: lingua-language-detector<3.0,>=2.1.1
Requires-Dist: pysubs2<2.0,>=1.8.0
Requires-Dist: scipy<2.0,>=1.15.3
Requires-Dist: sentence_transformers<6.0,>=4.1.0
Requires-Dist: tqdm<5.0,>=4.67.1
Requires-Dist: typer<1.0,>=0.16.0
Requires-Dist: gradio<6.0,>=5.41.1
Requires-Dist: nvidia_ml_py<13.0,>=12.575.51
Requires-Dist: pandas<3.0,>=2.3.1
Requires-Dist: psutil<8.0,>=7.0.0
Requires-Dist: hmmlearn<1.0,>=0.3.3
Provides-Extra: dev
Requires-Dist: ruff<1.0,>=0.12.4; extra == "dev"
Requires-Dist: pytest<9.0,>=8.4.0; extra == "dev"
Requires-Dist: coverage<8.0,>=7.9.2; extra == "dev"
Requires-Dist: playwright<2.0,>=1.54.0; extra == "dev"
Requires-Dist: requests<3.0,>=2.32.4; extra == "dev"
Provides-Extra: typecheck
Requires-Dist: mypy<2.0,>=1.16.1; extra == "typecheck"
Requires-Dist: types-PyYAML<7.0,>=6.0.12.20250516; extra == "typecheck"
Requires-Dist: scipy-stubs<2.0,>=1.16.0.2; python_version >= "3.11" and extra == "typecheck"
Requires-Dist: scipy-stubs==1.15.3.0; python_version < "3.11" and extra == "typecheck"
Requires-Dist: types-tqdm<5.0,>=4.67.0.20250516; extra == "typecheck"
Requires-Dist: pandas-stubs<3.0,>=2.3.0.250703; extra == "typecheck"
Requires-Dist: types-psutil<8.0,>=7.0.0.20250601; extra == "typecheck"
Dynamic: license-file
